django_etuovi/__init__.py
django_etuovi/apps.py
django_etuovi/enums.py
django_etuovi/etuovi.py
django_etuovi/items.py
django_etuovi/utils/__init__.py
django_etuovi/utils/testing.py
django_etuovi/utils/xml.py
django_etuovi-0.2.2.dist-info/licenses/LICENSE
django_etuovi-0.2.2.dist-info/METADATA
django_etuovi-0.2.2.dist-info/WHEEL
django_etuovi-0.2.2.dist-info/top_level.txt
django_etuovi-0.2.2.dist-info/RECORD
